{
  "date": "2026-06-07",
  "totalPlanned": 9,
  "entries": [
    {
      "id": "1780860517992-yb0abv5",
      "topicTitle": "Cloud Compliance Architecture: SOC 2 and HIPAA",
      "category": "Cloud Architecture",
      "completed": false
    },
    {
      "id": "1780860517992-9834irs",
      "topicTitle": "CloudFormation Stack Architecture and Nested Stacks",
      "category": "Infrastructure as Code",
      "completed": false
    },
    {
      "id": "1780860517992-rl2o4h7",
      "topicTitle": "Supply Chain Attack Vectors in CI/CD Pipelines",
      "category": "Cybersecurity",
      "completed": false
    },
    {
      "id": "1780860517992-oobsjaj",
      "topicTitle": "Distributed Lock Manager Architecture",
      "category": "System Design",
      "completed": false
    },
    {
      "id": "1780860517992-hu6z24k",
      "topicTitle": "Cloud Resource Tagging Strategy and Governance",
      "category": "Cloud Architecture",
      "completed": false
    },
    {
      "id": "1780860517992-euau486",
      "topicTitle": "Leader Election Algorithms in Distributed Systems",
      "category": "System Design",
      "completed": false
    },
    {
      "id": "1780860517992-ul566o8",
      "topicTitle": "Cloud-Native Database Selection Matrix",
      "category": "Cloud Architecture",
      "completed": false
    },
    {
      "id": "1780860517992-7n8k358",
      "topicTitle": "Autoscaling Policy Design: Predictive vs Reactive",
      "category": "Cloud Architecture",
      "completed": false
    },
    {
      "id": "1780860517992-8ywatms",
      "topicTitle": "Terraform Workspace vs Directory-Based Isolation",
      "category": "Infrastructure as Code",
      "completed": false
    }
  ],
  "createdAt": "2026-06-07T19:28:37.992Z"
}