{
  "date": "2026-03-13",
  "totalPlanned": 4,
  "entries": [
    {
      "id": "1773426828141-o8jqs15",
      "topicTitle": "Network Address Translation (NAT) Traversal Techniques",
      "category": "Networking",
      "completed": false
    },
    {
      "id": "1773426828141-xnjjk8z",
      "topicTitle": "Terraform State Management and Locking Architecture",
      "category": "Infrastructure as Code",
      "completed": false
    },
    {
      "id": "1773426828141-xzuc9pd",
      "topicTitle": "VPC Peering vs Transit Gateway: Architecture Trade-offs",
      "category": "Cloud Architecture",
      "completed": false
    },
    {
      "id": "1773426828141-wi08ghp",
      "topicTitle": "DNS-over-HTTPS Security Implications",
      "category": "Cybersecurity",
      "completed": false
    }
  ],
  "createdAt": "2026-03-13T18:33:48.141Z"
}